tasksflow/__init__.py
tasksflow/cache.py
tasksflow/common.py
tasksflow/executer.py
tasksflow/pool.py
tasksflow/task.py
tasksflow-0.3.1.dist-info/METADATA
tasksflow-0.3.1.dist-info/WHEEL
tasksflow-0.3.1.dist-info/licenses/LICENSE
tasksflow-0.3.1.dist-info/RECORD
