Metadata-Version: 2.3
Name: tasksflow
Version: 0.3.1
Summary: Handling Complex Workflows with Tasks
Author-email: 117503445 <t117503445@gmail.com>
License-File: LICENSE
Requires-Python: >=3.12
Requires-Dist: loguru>=0.7.2
